ConvoXML/AgentInterface.py
ConvoXML/Agents.py
ConvoXML/Context.py
ConvoXML/ConvoXML.py
ConvoXML/__init__.py
ConvoXML/tests.py
ConvoXML-1.1.dist-info/METADATA
ConvoXML-1.1.dist-info/WHEEL
ConvoXML-1.1.dist-info/top_level.txt
ConvoXML-1.1.dist-info/RECORD
