Metadata-Version: 2.1
Name: ConvoXML
Version: 1.1
Home-page: https://github.com/BlaiseLabs/ConvoXML
Requires-Dist: annotated-types (==0.6.0)
Requires-Dist: anyio (==3.7.1)
Requires-Dist: azure-common (==1.1.28)
Requires-Dist: azure-cosmosdb-nspkg (==2.0.2)
Requires-Dist: azure-cosmosdb-table (==1.0.6)
Requires-Dist: azure-nspkg (==3.0.2)
Requires-Dist: beautifulsoup4 (==4.12.2)
Requires-Dist: bs4 (==0.0.1)
Requires-Dist: cachetools (==5.3.2)
Requires-Dist: certifi (==2023.11.17)
Requires-Dist: cffi (==1.16.0)
Requires-Dist: charset-normalizer (==3.3.2)
Requires-Dist: cryptography (==41.0.5)
Requires-Dist: distro (==1.8.0)
Requires-Dist: exceptiongroup (==1.2.0)
Requires-Dist: google-ai-generativelanguage (==0.3.3)
Requires-Dist: google-api-core (==2.14.0)
Requires-Dist: google-auth (==2.23.4)
Requires-Dist: google-generativeai (==0.2.2)
Requires-Dist: googleapis-common-protos (==1.61.0)
Requires-Dist: grpcio (==1.59.3)
Requires-Dist: grpcio-status (==1.59.3)
Requires-Dist: h11 (==0.14.0)
Requires-Dist: httpcore (==1.0.2)
Requires-Dist: httpx (==0.25.1)
Requires-Dist: idna (==3.4)
Requires-Dist: openai (==1.3.4)
Requires-Dist: proto-plus (==1.22.3)
Requires-Dist: protobuf (==4.25.1)
Requires-Dist: pyasn1 (==0.5.1)
Requires-Dist: pyasn1-modules (==0.3.0)
Requires-Dist: pycparser (==2.21)
Requires-Dist: pydantic (==2.5.1)
Requires-Dist: pydantic-core (==2.14.3)
Requires-Dist: python-dateutil (==2.8.2)
Requires-Dist: requests (==2.31.0)
Requires-Dist: rsa (==4.9)
Requires-Dist: six (==1.16.0)
Requires-Dist: sniffio (==1.3.0)
Requires-Dist: soupsieve (==2.5)
Requires-Dist: tqdm (==4.66.1)
Requires-Dist: typing-extensions (==4.8.0)
Requires-Dist: urllib3 (==2.1.0)
Requires-Dist: xds-protos (==1.59.3)
